apperror/__init__.py
apperror-2.0.1.dist-info/LICENSE
apperror-2.0.1.dist-info/METADATA
apperror-2.0.1.dist-info/WHEEL
apperror-2.0.1.dist-info/top_level.txt
apperror-2.0.1.dist-info/RECORD
