Metadata-Version: 2.1
Name: apperror
Version: 2.0.1
Summary: Make logging and reporting of errors easier, more informative, and more "standard."
Home-page: https://github.com/CheggEng/apperror
Author: jric
Author-email: joshuarbox-junk1@yahoo.com
Project-URL: Bug Tracker, https://github.com/CheggEng/apperror/issues
Classifier: Programming Language :: Python :: 3
Classifier: License :: OSI Approved :: Apache Software License
Classifier: Operating System :: OS Independent
Classifier: Development Status :: 4 - Beta
Classifier: Intended Audience :: Developers
Classifier: Topic :: Software Development :: Libraries
Classifier: Topic :: Utilities
Classifier: Environment :: Console
Requires-Python: >=3.0
License-File: LICENSE
Requires-Dist: dumper (>=0.0)
